microscope_automation/__init__.py
microscope_automation/connectors/__init__.py
microscope_automation/connectors/connect_slidebook.py
microscope_automation/connectors/connect_zen_black.py
microscope_automation/connectors/connect_zen_blue.py
microscope_automation/connectors/connect_zen_blue_dummy.py
microscope_automation/hardware/RS232.py
microscope_automation/hardware/RS232_dummy.py
microscope_automation/hardware/__init__.py
microscope_automation/hardware/hardware_components.py
microscope_automation/hardware/hardware_control.py
microscope_automation/hardware/hardware_control_3i.py
microscope_automation/hardware/hardware_control_zeiss.py
microscope_automation/hardware/setup_microscope.py
microscope_automation/imports/__init__.py
microscope_automation/imports/intelligent_imaging_innovations.py
microscope_automation/imports/zeiss.py
microscope_automation/orchestrator/__init__.py
microscope_automation/orchestrator/find_positions.py
microscope_automation/orchestrator/microscope_automation.py
microscope_automation/orchestrator/write_zen_tiles_experiment.py
microscope_automation/samples/__init__.py
microscope_automation/samples/correct_background.py
microscope_automation/samples/draw_plate.py
microscope_automation/samples/find_cells.py
microscope_automation/samples/find_well_center.py
microscope_automation/samples/interactive_location_picker_pyqtgraph.py
microscope_automation/samples/positions_list.py
microscope_automation/samples/samples.py
microscope_automation/samples/segmentation_filters.py
microscope_automation/samples/setup_samples.py
microscope_automation/samples/tile_images.py
microscope_automation/samples/well_overview_segmentation.py
microscope_automation/samples/well_segmentation_refined.py
microscope_automation/settings/__init__.py
microscope_automation/settings/meta_data_file.py
microscope_automation/settings/preferences.py
microscope_automation/settings/slidebook_experiment_info.py
microscope_automation/settings/test_zen_experiment.py
microscope_automation-0.3.4.dist-info/LICENSE.txt
microscope_automation-0.3.4.dist-info/METADATA
microscope_automation-0.3.4.dist-info/WHEEL
microscope_automation-0.3.4.dist-info/top_level.txt
microscope_automation-0.3.4.dist-info/RECORD
