Metadata-Version: 2.1
Name: microscope-automation
Version: 0.3.4
Summary: Automation software for the AICS Microscopes.
Home-page: https://github.com/aics-int/microscope_automation
Author: Allen Institute for Cell Science
Author-email: fletcher.chapin@alleninstitute.org
License: Allen Institute Software License
Keywords: microscope_automation
Platform: UNKNOWN
Classifier: Development Status :: 2 - Pre-Alpha
Classifier: Intended Audience :: Developers
Classifier: License :: Free for non-commercial use
Classifier: Natural Language :: English
Classifier: Programming Language :: Python :: 3.7
Classifier: Programming Language :: Python :: 3.8
Requires-Python: >=3.7
Requires-Dist: tifffile (<2021,>=2020.8.25)
Requires-Dist: aicsimageio (<3.4,>=3.2.3)
Requires-Dist: pandas (<1.3,>=1.1.1)
Requires-Dist: numpy (<1.20,>=1.19.1)
Requires-Dist: pyyaml (<5.4,>=5.3.1)
Requires-Dist: pyqtgraph (<0.12,>=0.11.0)
Requires-Dist: PyQt5 (<5.16,>=5.12.3)
Requires-Dist: matplotlib (<3.4,>=3.3.1)
Requires-Dist: formlayout (<1.3,>=1.2.0)
Requires-Dist: lxml (<4.7,>=4.5.2)
Requires-Dist: psutil (<5.9,>=5.8.0)
Requires-Dist: pyserial (<3.5,>=3.4)
Requires-Dist: scikit-image (<0.19,>=0.16.2)
Requires-Dist: scipy (<1.7,>=1.6.0)
Requires-Dist: pywin32 (<301,>=227) ; platform_system == "Windows"
Provides-Extra: all
Requires-Dist: tifffile (<2021,>=2020.8.25) ; extra == 'all'
Requires-Dist: aicsimageio (<3.4,>=3.2.3) ; extra == 'all'
Requires-Dist: pandas (<1.3,>=1.1.1) ; extra == 'all'
Requires-Dist: numpy (<1.20,>=1.19.1) ; extra == 'all'
Requires-Dist: pyyaml (<5.4,>=5.3.1) ; extra == 'all'
Requires-Dist: pyqtgraph (<0.12,>=0.11.0) ; extra == 'all'
Requires-Dist: PyQt5 (<5.16,>=5.12.3) ; extra == 'all'
Requires-Dist: matplotlib (<3.4,>=3.3.1) ; extra == 'all'
Requires-Dist: formlayout (<1.3,>=1.2.0) ; extra == 'all'
Requires-Dist: lxml (<4.7,>=4.5.2) ; extra == 'all'
Requires-Dist: psutil (<5.9,>=5.8.0) ; extra == 'all'
Requires-Dist: pyserial (<3.5,>=3.4) ; extra == 'all'
Requires-Dist: scikit-image (<0.19,>=0.16.2) ; extra == 'all'
Requires-Dist: scipy (<1.7,>=1.6.0) ; extra == 'all'
Requires-Dist: black (>=19.10b0) ; extra == 'all'
Requires-Dist: codecov (>=2.1.4) ; extra == 'all'
Requires-Dist: flake8 (>=3.8.3) ; extra == 'all'
Requires-Dist: flake8-debugger (>=3.2.1) ; extra == 'all'
Requires-Dist: pytest (>=5.4.3) ; extra == 'all'
Requires-Dist: pytest-cov (>=2.9.0) ; extra == 'all'
Requires-Dist: pytest-raises (>=0.11) ; extra == 'all'
Requires-Dist: pytest-runner (>=5.2) ; extra == 'all'
Requires-Dist: pytest-html (>=2.1.1) ; extra == 'all'
Requires-Dist: mock (>=4.0.2) ; extra == 'all'
Requires-Dist: bumpversion (>=0.6.0) ; extra == 'all'
Requires-Dist: coverage (>=5.1) ; extra == 'all'
Requires-Dist: ipython (>=7.15.0) ; extra == 'all'
Requires-Dist: pyinstaller (>=4.0) ; extra == 'all'
Requires-Dist: Sphinx (<3.5,>=3) ; extra == 'all'
Requires-Dist: sphinx-rtd-theme (<0.6,>=0.4.3) ; extra == 'all'
Requires-Dist: tox (>=3.15.2) ; extra == 'all'
Requires-Dist: twine (>=3.1.1) ; extra == 'all'
Requires-Dist: wheel (>=0.34.2) ; extra == 'all'
Requires-Dist: pywin32 (<301,>=227) ; (platform_system == "Windows") and extra == 'all'
Provides-Extra: dev
Requires-Dist: black (>=19.10b0) ; extra == 'dev'
Requires-Dist: codecov (>=2.1.4) ; extra == 'dev'
Requires-Dist: flake8 (>=3.8.3) ; extra == 'dev'
Requires-Dist: flake8-debugger (>=3.2.1) ; extra == 'dev'
Requires-Dist: pytest (>=5.4.3) ; extra == 'dev'
Requires-Dist: pytest-cov (>=2.9.0) ; extra == 'dev'
Requires-Dist: pytest-raises (>=0.11) ; extra == 'dev'
Requires-Dist: pytest-runner (>=5.2) ; extra == 'dev'
Requires-Dist: pytest-html (>=2.1.1) ; extra == 'dev'
Requires-Dist: mock (>=4.0.2) ; extra == 'dev'
Requires-Dist: bumpversion (>=0.6.0) ; extra == 'dev'
Requires-Dist: coverage (>=5.1) ; extra == 'dev'
Requires-Dist: ipython (>=7.15.0) ; extra == 'dev'
Requires-Dist: pyinstaller (>=4.0) ; extra == 'dev'
Requires-Dist: Sphinx (<3.5,>=3) ; extra == 'dev'
Requires-Dist: sphinx-rtd-theme (<0.6,>=0.4.3) ; extra == 'dev'
Requires-Dist: tox (>=3.15.2) ; extra == 'dev'
Requires-Dist: twine (>=3.1.1) ; extra == 'dev'
Requires-Dist: wheel (>=0.34.2) ; extra == 'dev'
Provides-Extra: setup
Provides-Extra: test
Requires-Dist: black (>=19.10b0) ; extra == 'test'
Requires-Dist: codecov (>=2.1.4) ; extra == 'test'
Requires-Dist: flake8 (>=3.8.3) ; extra == 'test'
Requires-Dist: flake8-debugger (>=3.2.1) ; extra == 'test'
Requires-Dist: pytest (>=5.4.3) ; extra == 'test'
Requires-Dist: pytest-cov (>=2.9.0) ; extra == 'test'
Requires-Dist: pytest-raises (>=0.11) ; extra == 'test'
Requires-Dist: pytest-runner (>=5.2) ; extra == 'test'
Requires-Dist: pytest-html (>=2.1.1) ; extra == 'test'
Requires-Dist: mock (>=4.0.2) ; extra == 'test'
